asldatacollector/assets/alphabet.png
asldatacollector/assets/encsa.txt
asldatacollector/cli.py
asldatacollector/collect/__init__.py
asldatacollector/collect/collect.py
asldatacollector/collect/google/__init__.py
asldatacollector/collect/google/key.py
asldatacollector/collect/google/storage.py
asldatacollector/process/__init__.py
asldatacollector/process/dataset.py
asldatacollector/utils/__init__.py
asldatacollector/utils/helpers.py
asldatacollector/utils/samples.py
asldatacollector/utils/stats.py
asldatacollector-0.0.6.dist-info/LICENSE
asldatacollector-0.0.6.dist-info/METADATA
asldatacollector-0.0.6.dist-info/WHEEL
asldatacollector-0.0.6.dist-info/entry_points.txt
asldatacollector-0.0.6.dist-info/RECORD
