Metadata-Version: 2.1
Name: asldatacollector
Version: 0.0.6
Summary: Package for collecting data and transforming to dataset
Author: Popis
Author-email: piotrpopis98@icloud.com
Requires-Python: >=3.9,<4.0
Classifier: Programming Language :: Python :: 3
Classifier: Programming Language :: Python :: 3.9
Classifier: Programming Language :: Python :: 3.10
Classifier: Programming Language :: Python :: 3.11
Classifier: Programming Language :: Python :: 3.12
Classifier: Programming Language :: Python :: 3.13
Requires-Dist: cryptography (>=43.0.0,<44.0.0)
Requires-Dist: google-api-python-client (>=2.142.0,<3.0.0)
Requires-Dist: google-auth (>=2.34.0,<3.0.0)
Requires-Dist: google-auth-httplib2 (>=0.2.0,<0.3.0)
Requires-Dist: google-auth-oauthlib (>=1.2.1,<2.0.0)
Requires-Dist: mediapipe (>=0.10.14)
Requires-Dist: numpy (>=2.0.0,<3.0.0)
Requires-Dist: opencv-python (>=4.10.0.84)
Requires-Dist: psutil (>=6.0.0,<7.0.0)
Requires-Dist: tabulate (>=0.9.0,<0.10.0)
Requires-Dist: typer (>=0.12.4,<0.13.0)
